README.md
setup.py
direct_mmap/Makefile
direct_mmap/__init__.py
direct_mmap/main.py
direct_mmap.egg-info/PKG-INFO
direct_mmap.egg-info/SOURCES.txt
direct_mmap.egg-info/dependency_links.txt
direct_mmap.egg-info/top_level.txt
direct_mmap/cpp/Makefile
direct_mmap/cpp/memmap.cpp
direct_mmap/cpp/memmap.pyi
direct_mmap/cpp/memmap.so